<annotation>
	<folder>images</folder>
	<filename>adidas Fake 772.jpg</filename>
	<path>C:\Users\Pc\Desktop\Yolov3Custom-master\labelImg\images\adidas Fake 772.jpg</path>
	<source>
		<database>Unknown</database>
	</source>
	<size>
		<width>139</width>
		<height>107</height>
		<depth>1</depth>
	</size>
	<segmented>0</segmented>
	<object>
		<name>adidas Fake</name>
		<pose>Unspecified</pose>
		<truncated>0</truncated>
		<difficult>0</difficult>
		<bndbox>
			<xmin>23</xmin>
			<ymin>25</ymin>
			<xmax>125</xmax>
			<ymax>90</ymax>
		</bndbox>
	</object>
</annotation>
